sujal_ml/__init__.py
sujal_ml/sgd.py
sujal_ml-0.0.3.dist-info/licenses/LICENSE
sujal_ml-0.0.3.dist-info/METADATA
sujal_ml-0.0.3.dist-info/WHEEL
sujal_ml-0.0.3.dist-info/top_level.txt
sujal_ml-0.0.3.dist-info/RECORD
