Metadata-Version: 2.4
Name: sujal_ml
Version: 0.0.3
Summary: A Python package for trying out ML algorithms, also serves a package for DA2401 assignments.
Author-email: Sujal Kumar <sujaljayantkumar06@gmail.com>
Classifier: Programming Language :: Python :: 3
Classifier: License :: OSI Approved :: MIT License
Classifier: Operating System :: OS Independent
Requires-Python: >=3.9
License-File: LICENSE
Requires-Dist: numpy>=1.24
Dynamic: license-file
